real_estate_realtor_com/realtor.py
real_estate_realtor_com-0.0.7.dist-info/METADATA
real_estate_realtor_com-0.0.7.dist-info/WHEEL
real_estate_realtor_com-0.0.7.dist-info/top_level.txt
real_estate_realtor_com-0.0.7.dist-info/RECORD
