Metadata-Version: 2.1
Name: real-estate-realtor-com
Version: 0.0.7
Summary: PyPI Package for Real estate python package
Home-page: https://github.com/circles-zone/real-estate-realtor.com-selenium-imp-local-python-package
Author: Circles
Author-email: info@circles.life
Classifier: Programming Language :: Python :: 3
Classifier: License :: Other/Proprietary License
Classifier: Operating System :: OS Independent
Requires-Dist: mysqlclient
Requires-Dist: importer-local >=0.0.33
Requires-Dist: logger-local >=0.0.55
Requires-Dist: storage-local >=0.1.6
Requires-Dist: database-without-orm-local >=0.0.68
Requires-Dist: location-local >=0.0.23
Requires-Dist: entity-type-local >=0.0.12
Requires-Dist: logzio-python-handler >=4.1.1
Requires-Dist: opencage >=2.3.0
Requires-Dist: selenium
Requires-Dist: pandas
Requires-Dist: sqlalchemy
